top/core/__init__.py
top/core/encoding.py
top/core/task.py
top/core/tracker.py
top/gunicorn/__init__.py
top/gunicorn/hooks.py
top/gunicorn/testapp.py
top/integration.py
top/redis/__init__.py
top/redis/tracker.py
top/restapi/__init__.py
top/restapi/tracker.py
top/tui/__init__.py
top/tui/column.py
top/tui/row.py
top/utils.py
top/web/__init__.py
top/web/colour.py
top/web/main.py
top/web/noise.py
top/web/random_requests.py
top/web/task.py
top/web/web_columns.py
top_framework-0.3.2.dist-info/WHEEL
top_framework-0.3.2.dist-info/entry_points.txt
top_framework-0.3.2.dist-info/METADATA
top_framework-0.3.2.dist-info/RECORD
