Metadata-Version: 2.1
Name: top-framework
Version: 0.3.2
Summary: Python framework for creating UNIX top like TUI applications easily
Home-page: https://github.com/tradingstrategy-ai/top-framework
License: MIT
Keywords: cli,UNIX,TUI
Author: Mikko Ohtamaa
Author-email: mikko@opensourcehacker.com
Requires-Python: >=3.9,<4.0
Classifier: License :: OSI Approved :: MIT License
Classifier: Programming Language :: Python :: 3
Classifier: Programming Language :: Python :: 3.9
Classifier: Programming Language :: Python :: 3.10
Classifier: Programming Language :: Python :: 3.11
Provides-Extra: docs
Provides-Extra: gunicorn
Requires-Dist: Sphinx (>=5.1.1,<6.0.0) ; extra == "docs"
Requires-Dist: dataclasses-json (>=0.5.7,<0.6.0)
Requires-Dist: emoji-country-flag (>=1.3.1,<2.0.0)
Requires-Dist: furo (>=2022.6.21,<2023.0.0) ; extra == "docs"
Requires-Dist: gunicorn (>=20.1.0,<21.0.0) ; extra == "gunicorn"
Requires-Dist: iso8601 (>=1.0.2,<2.0.0)
Requires-Dist: python-lorem (>=1.1.2,<2.0.0) ; extra == "gunicorn"
Requires-Dist: redispy (>=3.0.0,<4.0.0)
Requires-Dist: sphinx-autodoc-typehints (>=1.16.0,<2.0.0) ; extra == "docs"
Requires-Dist: sphinx-sitemap (>=2.2.0,<3.0.0) ; extra == "docs"
Requires-Dist: textual (>=0.1.18,<0.2.0)
Requires-Dist: typer (>=0.6.1,<0.7.0)
Project-URL: Repository, https://github.com/tradingstrategy-ai/top-framework
